tracking/__init__.py
tracking/abstract_tracking.py
tracking/config.py
tracking/landmarks.py
tracking/webcam.py
tracking/enums/__init__.py
tracking/enums/finger.py
tracking/enums/side.py
tracking/enums/tracking_type.py
tracking/exceptions/__init__.py
tracking/exceptions/incorrect_instance.py
tracking/exceptions/invalid_flag.py
tracking/face_tracking/__init__.py
tracking/face_tracking/abstract.py
tracking/face_tracking/constants.py
tracking/face_tracking/face.py
tracking/face_tracking/tracking.py
tracking/face_tracking/partials/__init__.py
tracking/face_tracking/partials/drawing_face.py
tracking/face_tracking/partials/infos_face.py
tracking/hand_tracking/__init__.py
tracking/hand_tracking/abstract.py
tracking/hand_tracking/constants.py
tracking/hand_tracking/hand.py
tracking/hand_tracking/tracking.py
tracking/hand_tracking/partials/__init__.py
tracking/hand_tracking/partials/drawing_hand.py
tracking/hand_tracking/partials/infos_hand.py
tracking/hand_tracking/partials/measures_hand.py
tracking/tasks/face_landmarker.task
tracking/tasks/hand_landmarker.task
tracking/utils/__init__.py
tracking/utils/drawing.py
tracking/utils/math.py
tracking_py-1.1.1.dist-info/METADATA
tracking_py-1.1.1.dist-info/WHEEL
tracking_py-1.1.1.dist-info/top_level.txt
tracking_py-1.1.1.dist-info/RECORD
